[
    {
        "id": 18082950019160578,
        "created_at": 1582076957,
        "text": "\ud83d\udc99 Amorcito !!!! \ud83d\ude0b",
        "owner": {
            "id": "1676217155",
            "is_verified": false,
            "profile_pic_url": "https://scontent-lax3-2.cdninstagram.com/v/t51.2885-19/s150x150/13732339_554330008101813_1669256065_a.jpg?_nc_ht=scontent-lax3-2.cdninstagram.com&_nc_ohc=hJYxf0PamsUAX9CJbqX&oh=a0249a950151e5224cb9d494c679a54d&oe=5EE78E98",
            "username": "aguavidapremiumwater"
        },
        "likes_count": 0,
        "answers": []
    },
    {
        "id": 18116918149079614,
        "created_at": 1582076876,
        "text": "2 Amorcito is my fav",
        "owner": {
            "id": "194625594",
            "is_verified": false,
            "profile_pic_url": "https://scontent-lax3-2.cdninstagram.com/v/t51.2885-19/s150x150/84304581_124929272170555_3581803670309699584_n.jpg?_nc_ht=scontent-lax3-2.cdninstagram.com&_nc_ohc=SbHVAJkkoyAAX_wpIuG&oh=d82df1d0f0bd863a92e2a4c364532a9e&oe=5EC3D8C4",
            "username": "irenediazmusic"
        },
        "likes_count": 0,
        "answers": []
    }
]